pycontext/__init__.py
pycontext/context.py
pycontext/reader/__init__.py
pycontext/reader/reader.py
pycontext/reader/descriptor/__init__.py
pycontext/reader/descriptor/context_xml_reader.py
pycontext/reader/descriptor/web_xml_reader.py
pycontext/reader/environment/__init__.py
pycontext/reader/environment/envreader.py
pycontext/resolver/__init__.py
pycontext/resolver/ldapresolver.py
pycontext/resolver/resolver.py
pycontext/tool/__init__.py
pycontext/tool/typeparser.py
ilb_pycontext-2.1.0.dist-info/LICENSE
ilb_pycontext-2.1.0.dist-info/METADATA
ilb_pycontext-2.1.0.dist-info/WHEEL
ilb_pycontext-2.1.0.dist-info/top_level.txt
ilb_pycontext-2.1.0.dist-info/RECORD
